miakosections/__init__.py
miakosections/__main__.py
miakosections/helpers.py
miakosections/py.typed
miakosections/resources.py
miakosections/sections.py
miakosections-0.1.0.dist-info/LICENSE
miakosections-0.1.0.dist-info/METADATA
miakosections-0.1.0.dist-info/WHEEL
miakosections-0.1.0.dist-info/entry_points.txt
miakosections-0.1.0.dist-info/RECORD
