Metadata-Version: 2.1
Name: miakosections
Version: 0.1.0
Summary: miakosections
Home-page: https://github.com/DanBeranek/miakosections
License: MIT
Author: Daniel Beranek
Author-email: daniel.beraanek@gmail.com
Requires-Python: >=3.10.0,<3.12
Classifier: Development Status :: 2 - Pre-Alpha
Classifier: License :: OSI Approved :: MIT License
Classifier: Programming Language :: Python :: 3
Classifier: Programming Language :: Python :: 3.10
Classifier: Programming Language :: Python :: 3.11
Requires-Dist: click (>=8.0.1)
Requires-Dist: concreteproperties (>=0.6.2,<0.7.0)
Project-URL: Changelog, https://github.com/DanBeranek/miakosections/releases
Project-URL: Documentation, https://DanBeranek.github.io/miakosections
Project-URL: Repository, https://github.com/DanBeranek/miakosections
